tapitas/Diffusion_Progress.py
tapitas/__init__.py
tapitas/output_func.py
tapitas/subclusters_progress.py
tapitas/core_objs/__init__.py
tapitas/core_objs/neighbor_pair.py
tapitas/core_objs/node.py
tapitas/core_objs/progress_link.py
tapitas/core_objs/progression_graph.py
tapitas/core_objs/shift_graph.py
tapitas/core_objs/shifting_link.py
tapitas/core_objs/subcluster.py
tapitas/utils/__init__.py
tapitas/utils/weightedquickunion.py
tapitas/utils/exporter/__init__.py
tapitas/utils/exporter/output_objects.py
tapitas/utils/exporter/to_anime.py
tapitas/utils/exporter/to_csv.py
tapitas/utils/exporter/to_shpfile.py
tapitas/utils/exporter/to_svgs.py
tapitas-0.0.5.dist-info/METADATA
tapitas-0.0.5.dist-info/RECORD
tapitas-0.0.5.dist-info/WHEEL
tapitas-0.0.5.dist-info/top_level.txt
