Metadata-Version: 2.1
Name: tapitas
Version: 0.0.5
Summary: A data exploration and visualization algorithm for understanding diffusion process.
Home-page: https://bitbucket.org/wcchin/TaPiTaS
Author: Benny Chin
Author-email: wcchin.88@gmail.com
License: LICENSE.txt
Keywords: point diffusion subcluster progress
Platform: UNKNOWN
Classifier: Development Status :: 3 - Alpha
Classifier: Intended Audience :: Science/Research
Classifier: Topic :: Scientific/Engineering :: GIS
Classifier: License :: OSI Approved :: MIT License
Classifier: Programming Language :: Python :: 3.5
Requires-Dist: numpy
Requires-Dist: scipy
Requires-Dist: pandas
Requires-Dist: geopandas
Requires-Dist: shapely
Requires-Dist: descartes
Requires-Dist: matplotlib
Requires-Dist: seaborn
